LICENCE.txt
README.md
setup.py
linear_regression_model_lab/__init__.py
linear_regression_model_lab/linear_regression_model.py
linear_regression_model_lab.egg-info/PKG-INFO
linear_regression_model_lab.egg-info/SOURCES.txt
linear_regression_model_lab.egg-info/dependency_links.txt
linear_regression_model_lab.egg-info/requires.txt
linear_regression_model_lab.egg-info/top_level.txt