Metadata-Version: 2.1
Name: linear_regression_model_lab
Version: 1.0.0
Summary: Package doing linear regression
Home-page: http://pypi.python.org/pypi/linear_regression_model_lab/
Author: Guerinik Abderrahmane
Author-email: ca.guerinik@esi-sba.dz
License: LICENSE.txt
License-File: LICENCE.txt
Requires-Dist: linear_regression_model_lab
